django_sightline-0.1.0.dist-info/licenses/LICENSE
sightline/__init__.py
sightline/admin.py
sightline/apps.py
sightline/settings.py
sightline/tests.py
sightline/utils.py
sightline/views.py
sightline/locale/it/LC_MESSAGES/django.mo
sightline/locale/it/LC_MESSAGES/django.po
sightline/middleware/__init__.py
sightline/middleware/visit.py
sightline/migrations/0001_initial.py
sightline/migrations/__init__.py
sightline/models/__init__.py
sightline/models/base.py
sightline/models/visit.py
sightline/static/admin/js/charts.js
sightline/static/admin/js/vendor/d3/d3.v7.min.js
sightline/static/admin/js/vendor/topojson/topojson.3.0.2.js
sightline/static/admin/js/vendor/versor/versor.0.2.js
sightline/templates/admin/dashboard.html
sightline/templates/fragments/metrics.html
django_sightline-0.1.0.dist-info/METADATA
django_sightline-0.1.0.dist-info/WHEEL
django_sightline-0.1.0.dist-info/top_level.txt
django_sightline-0.1.0.dist-info/RECORD
