Metadata-Version: 2.4
Name: django-sightline
Version: 0.1.0
Summary: Smart, privacy-friendly site analytics for Django. Track visits, popular pages, referrers, and more — directly from the admin dashboard.
Home-page: https://github.com/francescoridolfi/django-sightline
Author: Francesco Ridolfi
Author-email: francesco.ridolfi.02@gmail.com
Classifier: Framework :: Django
Classifier: Programming Language :: Python
Classifier: Programming Language :: Python :: 3
Classifier: License :: OSI Approved :: MIT License
Classifier: Operating System :: OS Independent
Requires-Python: >=3.7
License-File: LICENSE
Requires-Dist: Django>=3.2
Requires-Dist: user-agents>=2.2.0
Dynamic: author
Dynamic: author-email
Dynamic: classifier
Dynamic: description
Dynamic: description-content-type
Dynamic: home-page
Dynamic: license-file
Dynamic: requires-dist
Dynamic: requires-python
Dynamic: summary
